<odoo>
  <data>
    <!-- explicit list view definition -->
    <record id="purchase_request_type_form_inherit" model="ir.ui.view">
        <field name="name">purchase.request_type.form</field>
        <field name="model">purchase.request</field>
        <field name="inherit_id" ref="purchase_request.view_purchase_request_form"/>
        <field name="arch" type="xml">
            <h1 position="after">
                <field name="is_expense" string="Note de frais"/><label for="is_expense"/>
            </h1>
            <xpath expr="//sheet/h1/field[@name='name']" position="attributes">
                <attribute name="attrs">{'readonly': True}</attribute>
            </xpath>
            <xpath expr="//sheet//group/group/field[@name='assigned_to']" position="after">
                <field name="is_for_project" widget='boolean_button' attrs="{'readonly': [('is_editable','=', False)],}" groups="purchase_request_type.group_purchase_request_type"/>
                <field name='purchase_type' attrs="{'readonly': [('is_editable','=', False)], 'required': True}"/>
                <field name='sale_order' string="Devis" attrs="{'required': [('is_for_project','=', True)], 'invisible': [('is_for_project', '=', False)],}" domain="[('state', 'in', ('done', 'False')),]" options="{'no_create': True}"/>
            </xpath>
            <xpath expr="//sheet//group/group[2]/field[@name='description']" position="attributes">
                <attribute name="attrs">{'required':[('purchase_type', '!=', 'project')]}</attribute>
            </xpath>
            <field name="picking_type_id" position="attributes">
                <attribute name="attrs">{'required':[('purchase_type', 'not in', ['travaux'])], 'invisible':[('purchase_type', 'in', ['travaux'])]}</attribute>
            </field>
            <xpath expr="//sheet/group/group[3]" position="after">
                <group>
                    <field name="date_required" string="Date de réception" attrs="{'readonly': [('is_editable','=', False)],}"/>
                </group>
            </xpath>
        </field>
    </record>
  </data>
</odoo>